epanet/__init__.py
epanet/_toolkit.so
epanet/libepanet2.so
epanet/toolkit.py
owa_epanet-2.3.3.data/data/epanet2.h
owa_epanet-2.3.3.data/data/epanet2_2.h
owa_epanet-2.3.3.data/data/epanet2_enums.h
owa_epanet-2.3.3.data/data/libepanet2.so
owa_epanet-2.3.3.data/data/runepanet
owa_epanet.libs/libepanet2-5d0617c6.so
owa_epanet-2.3.3.dist-info/METADATA
owa_epanet-2.3.3.dist-info/WHEEL
owa_epanet-2.3.3.dist-info/top_level.txt
owa_epanet-2.3.3.dist-info/RECORD
owa_epanet-2.3.3.dist-info/licenses/LICENSE
