Metadata-Version: 2.4
Name: owa-epanet
Version: 2.3.3
Summary: a thin wrapper for epanet hydraulic toolkit
Home-page: https://github.com/OpenWaterAnalytics/epanet-python
Author: Sam Hatchett
Author-email: samhatchett@gmail.com
License-File: LICENSE
Dynamic: author
Dynamic: author-email
Dynamic: description
Dynamic: description-content-type
Dynamic: home-page
Dynamic: license-file
Dynamic: summary
